{
  "parent": "minecraft:recipes/root",
  "rewards": {
    "recipes": [
      "minestuck:irradiated_steak"
    ]
  },
  "criteria": {
    "has_beef": {
      "trigger": "minecraft:inventory_changed",
      "conditions": {
        "items": [
          {
            "item": "minecraft:beef"
          }
        ]
      }
    },
    "has_the_recipe": {
      "trigger": "minecraft:recipe_unlocked",
      "conditions": {
        "recipe": "minestuck:irradiated_steak"
      }
    }
  },
  "requirements": [
    [
      "has_beef",
      "has_the_recipe"
    ]
  ]
}