{
  "type": "minecraft:gift",
  "pools": [
    {
      "bonus_rolls": 0.0,
      "entries": [
        {
          "type": "minecraft:item",
          "name": "minestuck:fire_poker",
          "weight": 3
        },
        {
          "type": "minecraft:item",
          "functions": [
            {
              "add": false,
              "count": {
                "type": "minecraft:uniform",
                "max": 10.0,
                "min": 5.0
              },
              "function": "minecraft:set_count"
            }
          ],
          "name": "minecraft:quartz",
          "weight": 10
        },
        {
          "type": "minecraft:item",
          "functions": [
            {
              "add": false,
              "count": {
                "type": "minecraft:uniform",
                "max": 5.0,
                "min": 2.0
              },
              "function": "minecraft:set_count"
            }
          ],
          "name": "minecraft:blaze_powder",
          "weight": 8
        },
        {
          "type": "minecraft:item",
          "functions": [
            {
              "add": false,
              "count": {
                "type": "minecraft:uniform",
                "max": 10.0,
                "min": 5.0
              },
              "function": "minecraft:set_count"
            }
          ],
          "name": "minecraft:nether_brick",
          "weight": 10
        }
      ],
      "name": "item",
      "rolls": 1.0
    },
    {
      "bonus_rolls": 0.0,
      "entries": [
        {
          "type": "minecraft:item",
          "functions": [
            {
              "add": false,
              "count": {
                "type": "minecraft:uniform",
                "max": 20.0,
                "min": 8.0
              },
              "function": "minecraft:set_count"
            }
          ],
          "name": "minestuck:cast_iron",
          "weight": 10
        },
        {
          "type": "minecraft:item",
          "functions": [
            {
              "add": false,
              "count": {
                "type": "minecraft:uniform",
                "max": 20.0,
                "min": 8.0
              },
              "function": "minecraft:set_count"
            }
          ],
          "name": "minestuck:chiseled_cast_iron",
          "weight": 6
        },
        {
          "type": "minecraft:item",
          "functions": [
            {
              "add": false,
              "count": {
                "type": "minecraft:uniform",
                "max": 20.0,
                "min": 8.0
              },
              "function": "minecraft:set_count"
            }
          ],
          "name": "minecraft:nether_bricks",
          "weight": 10
        },
        {
          "type": "minecraft:item",
          "functions": [
            {
              "add": false,
              "count": {
                "type": "minecraft:uniform",
                "max": 20.0,
                "min": 8.0
              },
              "function": "minecraft:set_count"
            }
          ],
          "name": "minecraft:red_nether_bricks",
          "weight": 6
        }
      ],
      "name": "block",
      "rolls": 1.0
    }
  ],
  "random_sequence": "minestuck:gameplay/consort_general/terrain/minestuck/heat"
}