{
    "textures": {
        "particle": "minestuck:block/machine/totem_lathe/bottom_left_front",
        "front":    "minestuck:block/machine/totem_lathe/bottom_left_front",
        "side":     "minestuck:block/machine/totem_lathe/bottom_left_side",
        "back":     "minestuck:block/machine/totem_lathe/bottom_left_back",
        "top":      "minestuck:block/machine/totem_lathe/bottom_left_top",
        "down":     "minestuck:block/machine/totem_lathe/down_left",
        "inside":   "minestuck:block/machine/totem_lathe/bottom_left_inside"
    },
    "elements": [
        {
            "from": [ 8, 0, 4 ],
            "to": [ 16, 16, 14 ],
            "faces": {
                "north": { "uv": [ 0, 0,  8, 16 ], "texture": "#front" },
                "east":  { "uv": [ 3, 0, 13, 16 ], "texture": "#side", "cullface": "east" },
                "south": { "uv": [ 8, 0, 16, 16 ], "texture": "#back" },
                "west":  { "uv": [ 0, 0, 10, 16 ], "texture": "#side" },
                "up":    { "uv": [ 8, 5, 16, 15 ], "texture": "#top", "cullface": "up" },
                "down":  { "uv": [ 8, 1, 16, 11 ], "texture": "#down", "cullface": "down" }
            }
        },
        {
            "name": "base",
            "from": [ 0, 0, 5 ],
            "to": [ 7, 2, 15 ],
            "faces": {
                "north": { "uv": [ 9, 14, 16, 16 ], "texture": "#front" },
                "east":  { "uv": [ 1, 14, 11, 16 ], "texture": "#down" },
                "south": { "uv": [ 0, 14,  7, 16 ], "texture": "#back" },
                "west":  { "uv": [ 5, 14, 15, 16 ], "texture": "#inside", "cullface": "west" },
                "up":    { "uv": [ 0,  6,  7, 16 ], "texture": "#top" },
                "down":  { "uv": [ 0,  0,  7, 10 ], "texture": "#down", "cullface": "down" }
            }
        },
        {
            "name": "card_slot",
            "from": [0, 2, 3],
            "to": [7, 13, 14],
            "faces": {
                "north": { "uv": [ 9, 3, 16, 14 ], "texture": "#front" },
                "east":  { "uv": [ 5, 3, 16, 14 ], "texture": "#side" },
                "south": { "uv": [ 0, 3,  7, 14 ], "texture": "#back" },
                "west":  { "uv": [ 3, 3, 14, 14 ], "texture": "#inside", "cullface": "west" },
                "up":    { "uv": [ 0, 4,  7, 15 ], "texture": "#top" },
                "down":  { "uv": [ 0, 1,  7, 12 ], "texture": "#down" }
            }
        },
        {
            "from": [0, 13, 6],
            "to": [7, 16, 14],
            "faces": {
                "north": { "uv": [ 9, 0, 16,  3 ], "texture": "#front" },
                "south": { "uv": [ 0, 0,  7,  3 ], "texture": "#back" },
                "west":  { "uv": [ 6, 0, 14,  3 ], "texture": "#inside", "cullface": "west" },
                "up":    { "uv": [ 0, 7,  7, 15 ], "texture": "#top", "cullface": "up" }
            }
        },
        {
            "from": [7, 0, 6],
            "to": [8, 16, 14],
            "faces": {
                "north": { "uv": [ 8, 0,  9, 16 ], "texture": "#front" },
                "south": { "uv": [ 7, 0,  8, 16 ], "texture": "#back" },
                "west":  { "uv": [ 7, 0, 14, 16 ], "texture": "#inside" },
                "up":    { "uv": [ 7, 7,  8, 15 ], "texture": "#top" },
                "down":  { "uv": [ 7, 1,  8,  9 ], "texture": "#down" }
            }
        },
        {
            "from": [9, 12, 3],
            "to": [16, 16, 4],
            "faces": {
                "north": { "uv": [ 0, 0, 7, 4 ], "texture": "#front" },
                "east":  { "uv": [ 0, 0, 1, 4 ], "texture": "#front" },
                "west":  { "uv": [ 6, 0, 7, 4 ], "texture": "#front" },
                "up":    { "uv": [ 0, 0, 7, 1 ], "texture": "#front", "cullface": "up" },
                "down":  { "uv": [ 0, 3, 7, 4 ], "texture": "#front" }
            }
        },
        {
            "name": "card_1",
            "from": [1, 13, 5],
            "to": [7, 15, 5],
            "faces": {
                "north": { "uv": [0, 2, 6, 4], "texture": "#top" },
                "south": { "uv": [6, 2, 0, 4], "texture": "#top" }
            }
        },
        {
            "name": "card_2",
            "from": [1, 13, 4],
            "to": [7, 15, 4],
            "faces": {
                "north": { "uv": [0, 2, 6, 4], "texture": "#top" },
                "south": { "uv": [6, 2, 0, 4], "texture": "#top" }
            }
        }
    ]
}